fustor_core/__init__.py
fustor_core/drivers.py
fustor_core/exceptions.py
fustor_core/models/__init__.py
fustor_core/models/config.py
fustor_core/models/log.py
fustor_core/models/states.py
fustor_core/utils/retry.py
fustor_core-0.2.16.dist-info/METADATA
fustor_core-0.2.16.dist-info/WHEEL
fustor_core-0.2.16.dist-info/top_level.txt
fustor_core-0.2.16.dist-info/RECORD
