Metadata-Version: 2.4
Name: fustor-core
Version: 0.2.16
Summary: Core components for Fustor services and plugins
Author-email: Huajin Wang <wanghuajin999@163.com>
Requires-Python: >=3.11
Requires-Dist: pydantic>=2.11.7
Provides-Extra: dev
Requires-Dist: pytest>=8.0.0; extra == "dev"
Requires-Dist: ruff>=0.1.0; extra == "dev"
Requires-Dist: mypy>=1.0.0; extra == "dev"
Requires-Dist: pytest-asyncio>=0.23.0; extra == "dev"
